<author lang="en"><documents><document><![CDATA[#FirstRow para ver a #NickLaw CCO de #PublicisGroup después #FeaturedSession con #GwynethPaltrow fundadora de #Goop… https://t.co/DiheElJi43]]></document><document><![CDATA[Midnight tunes. #vinyl #lp #nowspinning  #menahanstreetband #maketheroadbywalking #debutalbum #dunhamrecords… https://t.co/pyCmvoNOHv]]></document><document><![CDATA[Why are Iggy and Cardi on this post? That’s an insult to the popularity and sheer star power of nicki and an insult… https://t.co/ETTILNuELQ]]></document><document><![CDATA[@killashoots @pullinganangie @csuf It's a short news package! It would be a 5-10 minute interview if you can.]]></document><document><![CDATA[And, of course, despite having far more computing power that the Apollo program, the only information from the came… https://t.co/9deSx3DSlz]]></document><document><![CDATA[And everyone wonder why all trump nominees he pick are for to protect him from the justice department for his crimi… https://t.co/BdfPf0qCl4]]></document><document><![CDATA[Sounds about right. And to those who "dont care what people think", why you always telling myself others, you tryin… https://t.co/t3LCcHDVKw]]></document><document><![CDATA[Been at work since 3:00 pm yesterday... overnight shift came in at 11:00 pm yesterday... somehow I am the only one still awake.]]></document><document><![CDATA[Over from Manchester, UK and first time at the ice hockey. Won't be the last, we're @GoldenKnights fans from here o… https://t.co/t7LjYVIxN0]]></document><document><![CDATA[@Libertadores el facebook live no funciona no desde mi dispositivo móvil ni mi tv. No experimenten con… https://t.co/StcDDxrEmW]]></document><document><![CDATA[@ss_slacker For $20 a year, it feels worth a shot. There's also a 7-day trial]]></document><document><![CDATA[Shoutout to @TXSTFSA for having the CRAZIEST set for SPIRIT!!! Def deserve 1st place 👏👏]]></document><document><![CDATA[Manhattan College’s heroic intervention in the 1948 NAIB Basketball Tournamnet reminded the entire nation of the sa… https://t.co/t29IAa56FT]]></document><document><![CDATA[@John_Kavanagh What about us regular folks? I’ll be in Ireland on June. 😉 although, I’m not sure you’d learn much f… https://t.co/M801L0oxWr]]></document><document><![CDATA[$YY pretty big beat.  Stk was 140 I can see it gap up 10... Look what $BABA has done]]></document><document><![CDATA[After 3 weeks, driving 2,529 miles and seeing some amazing places through the US it’s time to come home #Chicago… https://t.co/pvD42VgiQM]]></document><document><![CDATA[#NATAM2019IN.... @INAthletic. ...@JLWhalley. @Athletics_GHS #NewProfilePic https://t.co/hsvMut98oJ]]></document><document><![CDATA[@JDVFL @RealBasedMAGA I disagree this Country was dumb enough to elect Obama twice. Thay are capable of voting for his sorry ass.]]></document><document><![CDATA[I would like to put myself out there as I did so much in the past and offer my assistance to any studio who might h… https://t.co/fel26VMRWG]]></document><document><![CDATA[@get_MERKT @adharms right by our section, those kids in front of us are about to learn how to cheer]]></document><document><![CDATA[this new alex jones and joe rogan podcast has me in 6 different dimensions right now]]></document><document><![CDATA[Centennial busts out a 6-0 run to pull ahead 13-6 with 2:54 left in the first. Four Chargers have scored, led by Wi… https://t.co/rMMpdaMLDB]]></document><document><![CDATA[The best in the business @AlGuido Congrats my brother. Keep guiding our ship to new heights!]]></document><document><![CDATA[@themanfronUNCLE I gotta head over to The V.A. In Wilmington for a Daggum Physical]]></document><document><![CDATA[@NASTYNOE98 Shit I always miss a spot sfter shaving so I gotta do it all over again haha]]></document><document><![CDATA[So, @JohnCornyn, what's the deal? I figured the @GOP planned on keeping their fascism on the down low. Quoting Muss… https://t.co/kxVacX709K]]></document><document><![CDATA[hi @blinkfitness could you refund your members who you tripled charged today without telling them! thanks! love to… https://t.co/JUkaNuW589]]></document><document><![CDATA[The Wolverines call timeout w/ 3:06 to play in the first quarter....  South Central 7, Wakefield 5  #HSOTScores #HoopState #NCHSAAMBB 🏀]]></document><document><![CDATA[@39KillerQueens @meanmugsue @TheRealDIGGZ_GC @Complex You are defending a guy who admits to showing with lots of yo… https://t.co/nGIYmIvv4A]]></document><document><![CDATA[@daviddebolt East Bay community college system chooses “King of New York” acting chancellor. https://t.co/pfGHraEdHL]]></document><document><![CDATA[Still getting after each other. Kudos to both Marquette and Villanova for their level of fight in this one. Both want it bad.]]></document><document><![CDATA[@news_store_com @AngelCIraq214 @FedEx @RepDonBeyer @HillaryClinton @BarackObama @VA8thCDDems @lowkell @timkaine… https://t.co/c5XKY7zYj6]]></document><document><![CDATA[#Memphis #MemphisTn are you ready?  @marshaambrosius performing LIVE on Friday, March 15 at @minglewoodhall with sp… https://t.co/0RNE2KHY7C]]></document><document><![CDATA[@_SJPeace_ @AOC To quote the great @billengvall “Here’s your sign!” ⬇️ https://t.co/6YxDQjqARg]]></document><document><![CDATA[@jackiembouvier I know!  I don't mind opinion. I just don't want to see it when people are purporting to be "news".]]></document><document><![CDATA[Check out this WOMEN'S 18KT WHITE GOLD DIAMONDS CASE DRESS WATCH. for $48,700.99 on OfferUp https://t.co/GTalb6M3Gj]]></document><document><![CDATA[But God made dogs he's trying to shut down Twitter now I did the best shutting down of his election at tronox like… https://t.co/yMIA4q1igb]]></document><document><![CDATA[Got to experience a much needed adventure to the Training Facility.Had WAY TO MUCH FUN today.Thank God for blessing… https://t.co/NRwe2ymzFO]]></document><document><![CDATA[Trump#45POTASS  IS AN EXPERT IN FOR PROFIT EDUCATIONAL INSTITUTIONS!  STUDENTS SUFFERING IS CRIMINAL!]]></document><document><![CDATA[An active week begins in #mnleg on #energy matters! First up, the #mnhouse considers #solar on schools. @PattyAcomb… https://t.co/0oGClRIhLv]]></document><document><![CDATA[They just want diallo to throw down a good dunk to end lol not a cupcake]]></document><document><![CDATA[I vacation where I do because I really like it there and because I'm terrified of @goathilltavern birthday announce… https://t.co/clsxCiHytn]]></document><document><![CDATA[How about using data and APIs instead of documents?  As we push to modernize government, let’s not forget the regul… https://t.co/ZhJhkqgueh]]></document><document><![CDATA[You already know @jordyn_wieber is the jumpsuit QUEEN! 👸🏽 #uclagymnastics]]></document><document><![CDATA[Lift off. #whipthemeringue #suburbhouseales @ Philadelphia Eagles https://t.co/4neyWPhhHO]]></document><document><![CDATA[@GGYOUNGBOY been the hottest person on YouTube for the last 10 weeks and on.... shhh]]></document><document><![CDATA[@enosarris is not only the most famous Eno he is clearly the most expert Eno in the world of craft beers. Hey… https://t.co/wWoltVqm2N]]></document><document><![CDATA[@chatta_girl I’m usually out in the field starting at 5 a.m., before the sun comes up. Today we went to five different locations.]]></document><document><![CDATA[@ArkansasSenate @ArkansasHouse @ArkAthTrainers #ARpx #ARleg March is National Athletic Training Month. We ask your… https://t.co/vZ1XMtu552]]></document><document><![CDATA[Happy Birthday Megan. I’m thankful everyday that you’re mine. ❤️ https://t.co/BGKlA0Uqva]]></document><document><![CDATA[Bravo-Young v Desanto. McKee v Storr.  Moran v Lee. Young v Bleise. Tomorrow morning is gonna be juicy]]></document><document><![CDATA[@GOPChairwoman @HouseGOP @mexico "Right is Right, just not Right here, Lefty" #WeThePeople We fight Harder.]]></document><document><![CDATA[Drinking a Flying Tigersault by @3floyds at @ThePintWL — https://t.co/efLBPg1ftW]]></document><document><![CDATA[@NickHaigler @F3LakeMurray @Palmetto200 @F3TopGunAO https://t.co/IgyCxMV5Tg]]></document><document><![CDATA[@svdate I read his nonsense and all my mind fabricated was I bet that he wishes snap of the finger labor or genie n… https://t.co/v7Cl2UvojI]]></document><document><![CDATA[@RealSaavedra I wander if she agrees of mass extermination of the Jews in Nazi Germany !  Will she open up Auschwitz?  HER hat is MAHA.]]></document><document><![CDATA[Phillip just walked over to me (and Judah’s bassinet next to me) and said “hey.... where’s the other one...”   He w… https://t.co/BHJCRkxU9J]]></document><document><![CDATA[It’s so easy to fall for each other I’m just hoping we catch one another]]></document><document><![CDATA[@Bryesha_Adams Good morning, Bryesha! I hope you have yourself a nice day at work, and a blessed day! Thanks for al… https://t.co/Qr9D3RhvGw]]></document><document><![CDATA[@myk_carr @coolcam101 @realDonaldTrump @FoxNews https://t.co/nwaHrj2jcX]]></document><document><![CDATA[Que no se olvide esto que sucedio sexenio pasado https://t.co/jGNoYeBji4]]></document><document><![CDATA[Unreal I got to be alive at the same time as this awesome and incomparable human. #ali]]></document><document><![CDATA[#puppypictures just became a slack channel at work. tears of joy heard all over the office. https://t.co/v4GGKqdShF]]></document><document><![CDATA[Gordon Hayward must have seen too many of those tweets about his $31m salary and 4ppg since the all star break..]]></document><document><![CDATA[N4TRQ-5 Near Tidewater Family Medical Care, Chesapeake, VA https://t.co/PBPtuqZ8lv #APRS 13b]]></document><document><![CDATA[Mohammed's Koran by Peter McLoughlin and Tommy Robinson https://t.co/gZ562MNuaQ]]></document><document><![CDATA[minority EC President candidates wouldn’t be difficult at all. Really encouraged by JD’s appointments.]]></document><document><![CDATA[On my way to St. Mary’s for the final day of action at the @CWOSSABball championships. Looking forward to what shou… https://t.co/uQdg4VWqHa]]></document><document><![CDATA[Trump says maybe U.S. will have a president for life someday https://t.co/ocWgXbGsLr]]></document><document><![CDATA[@NMazepin I'm truly happy you follow orders if you're going to rape someone and keep her your slave you might as we… https://t.co/D9Zjj7K2nl]]></document><document><![CDATA[Remember to inspire at least one person today my friends 💖 https://t.co/N3ZsHJuQqk]]></document><document><![CDATA[La vida te puede sorprender con momentos maravillosos o situaciones dolorosas. Aprende de las dos...]]></document><document><![CDATA[This is what usually happens, when a chic says NO, in a bar. Guess that dude won't be kissing no one else, for many… https://t.co/XKElcVLDFs]]></document><document><![CDATA[@leonardo_live #day1 #haiheliexpo2019 #aw109trekker #aw119kx #aw169 #vip #ems #helicopters #georgia #usa @ Georgia… https://t.co/NhxTXa9T9J]]></document><document><![CDATA[@peterbakernyt @nytimes @adamgoldmanNYT @matthewhaag https://t.co/sATnQeUPhI]]></document><document><![CDATA[Traveling Pinguinose with a Mini-Bobinose. @ Los Angeles, California https://t.co/dDZM8gtfGg]]></document><document><![CDATA[I Got a Job at Chuck E. Cheese and They Recycle Their Pizza! (WITH PROOF) https://t.co/kSqGApQUBp via @YouTube]]></document><document><![CDATA[@redsteeze @mullrainee YKNOW STEVE NO ONE CARES ABOUT YER OPINION. STICK TO WRITIN SPEECHES FER MY BUDDY DON AND SMARTEN UP! (THUMBS UP)]]></document><document><![CDATA[Ortiz shows you have to take some to get some delivering this right hand! #PhotoByDC #Boxing #Fighter #Athlete… https://t.co/Uu1UR5oOMM]]></document><document><![CDATA[@TheBirdAndBoo @VictorLicata1 @GiantsProfessor @Mitt_Fit @gimleteyemiami @KamVTV @RealSaavedra @BetoORourke… https://t.co/13wrF4JVs2]]></document><document><![CDATA[@JerryBushman @Cindyhurd @dbongino The cost of deceiving America for years is worth way more than a few million dollars]]></document><document><![CDATA[I never voted Conservative federally so they aren't losing my vote either...]]></document><document><![CDATA[Olivia Colman is a f’ing delight.   Best acceptance of the night.   #Oscars]]></document><document><![CDATA[@VGKLadies @VGKcoverage @knightsonice @DavidSchoenLVRJ @GoldenKnights @RP_Quigs @JesseGranger_ @FisherJillian… https://t.co/iAEPszUqLa]]></document><document><![CDATA[@Noe42267527 @juanburgos @LuisNegrito @VanesaVanHelsin En Querétaro también la sobrellevamos con Mobil, hasta que a… https://t.co/xiMZUHeoIK]]></document><document><![CDATA[@JacmupJim @Haudenschild_17 @MarshallRacing_ 🇨🇦, that sounds like an awesome way to spend the day! You can blame it… https://t.co/pXTGWPSrWA]]></document><document><![CDATA[@tickedoffJJ @steph93065 @BillOReilly @willchamberlain Then you have never listened to any agents there or have bee… https://t.co/AsViFTq5BY]]></document><document><![CDATA[@mildredmud @realDonaldTrump @POTUS @VP @PressSec @WhiteHouse @KellyannePolls @senatemajldr @GOPLeader @seanhannity… https://t.co/Ekn79IL2PR]]></document><document><![CDATA[Exactly... Some people don't get it man. They can't sign every single fan's item every single day...]]></document><document><![CDATA[A que hora me daran mi #Oscar como mejor actor por el papel de pendejo que interprete al creer que ella me amaba ?… https://t.co/iC1kYpVOnA]]></document><document><![CDATA[@poloniumman @Doctrine_Man That’s a perfect example. I could rattle off a hundred more I saw as a post PAO.]]></document><document><![CDATA[Do not be afraid to go out on a limb...that’s where the fruit is #lifeisgood 🦊 https://t.co/kQwoLogYuz]]></document><document><![CDATA[BELOW FREEZING for most of this 1st weekend of March!  Off/on drizzle Sat. with low travel impacts.  Sat night-Sun.… https://t.co/A9AsRA62En]]></document><document><![CDATA[@OmgTheRealMello @offendedbender @beehzy17 Mello join up I wanna shoot your body.]]></document><document><![CDATA[@RepBenMcAdams Yep I knew you would just vote with The fruitcake Nancy freaking idiot Pelosi.   This is why people… https://t.co/c92BzPRF4V]]></document><document><![CDATA[Let’s talk about Nancy @SpeakerPelosi rocking her ashes like a boss. ❤️]]></document><document><![CDATA[@Lin_Manuel In The Heights on Vinyl.  Best 50 bucs I've ever spent!  Love your work so much :) https://t.co/XfTWENq3sn]]></document><document><![CDATA[@DailyMirror Looks like a 3 year old got ahold of her moms lipstick. BUT it’s a grown woman.. and her period.. blood...]]></document><document><![CDATA[@Eastonbauer @Ilhan Everything.  Why have you not called out Trump for saying and tweeting way worse.  He is presid… https://t.co/uygks1BnAl]]></document><document><![CDATA[Always read the box... I just wanted some relief hopefully I can make it the next few hours in class #bfgotmesick… https://t.co/LyBNilHLvu]]></document></documents></author>